constyle/__init__.py
constyle/__main__.py
constyle/_attributes.py
constyle/_style.py
constyle/custom_colours.py
constyle/py.typed
constyle-2.0.5.dist-info/LICENSE
constyle-2.0.5.dist-info/METADATA
constyle-2.0.5.dist-info/WHEEL
constyle-2.0.5.dist-info/entry_points.txt
constyle-2.0.5.dist-info/RECORD
