Metadata-Version: 2.1
Name: constyle
Version: 2.0.5
Summary: A Python library to add style to your console.
Home-page: https://github.com/abrahammurciano/python-constyle
License: GPLv3
Keywords: terminal,console,style,color,colors,colour,colours,ansi
Author: Abraham Murciano
Author-email: abrahammurciano@gmail.com
Requires-Python: >=3.7,<4.0
Classifier: License :: Other/Proprietary License
Classifier: Programming Language :: Python :: 3
Classifier: Programming Language :: Python :: 3.7
Classifier: Programming Language :: Python :: 3.8
Classifier: Programming Language :: Python :: 3.9
Classifier: Programming Language :: Python :: 3.10
Classifier: Programming Language :: Python :: 3.11
Requires-Dist: attributes-doc (>=0.3.0)
Requires-Dist: importlib-metadata (>=4.11.0)
Project-URL: Documentation, https://abrahammurciano.github.io/python-constyle/constyle
Project-URL: Repository, https://github.com/abrahammurciano/python-constyle
